raman_rabi/__init__.py
raman_rabi/test.py
raman_rabi-0.1.dist-info/DESCRIPTION.rst
raman_rabi-0.1.dist-info/METADATA
raman_rabi-0.1.dist-info/RECORD
raman_rabi-0.1.dist-info/WHEEL
raman_rabi-0.1.dist-info/metadata.json
raman_rabi-0.1.dist-info/top_level.txt
