Metadata-Version: 2.0
Name: raman-rabi
Version: 0.1
Summary: Parameter fitting for Raman-Rabi electron-nuclear spin flip-flop transitions in NV centers.
Home-page: https://github.com/phys201/raman_rabi
Author: Taylor Patti, Jamelle Watson-Daniels, Soumya Ghosh
Author-email: soumya_ghosh@g.harvard.edu
License: GNU LGPL
Platform: UNKNOWN
Requires-Dist: numpy
